{
    "blogs":[
        {
            "section": "MINDFUL LIVING",
            "heading":"How To Officially Break Up With Amazon Prime (It's Hard, We Know!)",
            "image": "pexels-daria-shevtsova-1070053.jpg",
            "category": "self"
        },
        {
            "section": "MINDFUL LIVING",
            "heading":"How To Officially Break Up With Amazon Prime (It's Hard, We Know!)",
            "image": "pexels-daria-shevtsova-1070053.jpg",
            "category": "self"
        },
        {
            "section": "MINDFUL LIVING",
            "heading":"How To Officially Break Up With Amazon Prime (It's Hard, We Know!)",
            "image": "pexels-daria-shevtsova-1070053.jpg",
            "category": "self"
        },
        {
            "section": "MINDFUL LIVING",
            "heading":"How To Officially Break Up With Amazon Prime (It's Hard, We Know!)",
            "image": "pexels-daria-shevtsova-1070053.jpg",
            "category": "self"
        },
        {
            "section": "MINDFUL LIVING",
            "heading":"How To Officially Break Up With Amazon Prime (It's Hard, We Know!)",
            "image": "pexels-daria-shevtsova-1070053.jpg",
            "category": "self"
        }
    ]
}